{
	"configurations" : 
	[
		{
			"directories" : 
			[
				{
					"build" : ".",
					"jsonFile" : "directory-.-Debug-d0094a50bb2071803777.json",
					"minimumCMakeVersion" : 
					{
						"string" : "3.22"
					},
					"projectIndex" : 0,
					"source" : ".",
					"targetIndexes" : 
					[
						0
					]
				}
			],
			"name" : "Debug",
			"projects" : 
			[
				{
					"directoryIndexes" : 
					[
						0
					],
					"name" : "beta_ajedrez",
					"targetIndexes" : 
					[
						0
					]
				}
			],
			"targets" : 
			[
				{
					"directoryIndex" : 0,
					"id" : "beta_ajedrez::@6890427a1f51a3e7e1df",
					"jsonFile" : "target-beta_ajedrez-Debug-728d29ffcf519eefce76.json",
					"name" : "beta_ajedrez",
					"projectIndex" : 0
				}
			]
		}
	],
	"kind" : "codemodel",
	"paths" : 
	{
		"build" : "C:/Users/renat/OneDrive/Desktop/universidad_ciclo_3/progra3/beta_ajedrez/cmake-build-debug",
		"source" : "C:/Users/renat/OneDrive/Desktop/universidad_ciclo_3/progra3/beta_ajedrez"
	},
	"version" : 
	{
		"major" : 2,
		"minor" : 3
	}
}
